scrapy_db/__init__.py
scrapy_db/db.py
scrapy_db/defaults.py
scrapy_db/dupefilter.py
scrapy_db/queue.py
scrapy_db/scheduler.py
scrapy_db/spiders.py
scrapy_db/utils.py
scrapy_db-0.0.5.dist-info/LICENSE
scrapy_db-0.0.5.dist-info/METADATA
scrapy_db-0.0.5.dist-info/WHEEL
scrapy_db-0.0.5.dist-info/RECORD
