Metadata-Version: 2.1
Name: scrapy-db
Version: 0.0.5
Summary: Similar to [scrapy-redis](https://github.com/rmax/scrapy-redis), using the database as a queue, database-based scrapy components.
Home-page: https://github.com/libra146/scrapy-db/blob/main/README.md
License: GPL-3.0-only
Author: libra146
Author-email: shumeipai146@gmail.com
Requires-Python: >=3.7,<4.0
Classifier: License :: OSI Approved :: GNU General Public License v3 (GPLv3)
Classifier: Natural Language :: English
Classifier: Programming Language :: Python :: 3
Classifier: Programming Language :: Python :: 3.7
Classifier: Programming Language :: Python :: 3.8
Classifier: Programming Language :: Python :: 3.9
Classifier: Programming Language :: Python :: 3.10
Classifier: Programming Language :: Python :: 3.11
Requires-Dist: peewee (>=3.16.0,<4.0.0)
Requires-Dist: pymysql (>=1.0.3,<2.0.0)
Requires-Dist: scrapy (>=2.7.0,<3.0.0)
Project-URL: Documentation, https://github.com/libra146/scrapy-db/blob/main/README.md
Project-URL: Repository, https://github.com/libra146/scrapy-db
